rrc_fields/__init__.py
rrc_fields/parser.py
rrc_fields/layouts/__init__.py
rrc_fields/layouts/forms.py
rrc_fields/layouts/gas.py
rrc_fields/layouts/general.py
rrc_fields/layouts/lookups.py
rrc_fields/layouts/market.py
rrc_fields/layouts/oil.py
rrc_fields/layouts/registry.py
rrc_fields-1.1.0.dist-info/METADATA
rrc_fields-1.1.0.dist-info/WHEEL
rrc_fields-1.1.0.dist-info/top_level.txt
rrc_fields-1.1.0.dist-info/RECORD
