Metadata-Version: 2.4
Name: rrc-fields
Version: 1.1.0
Summary: A parser for Texas RRC field data in EBCDIC format
Author-email: Marcus Salinas <12.marcus.salinas@gmail.com>
Classifier: Programming Language :: Python :: 3
Classifier: License :: OSI Approved :: MIT License
Classifier: Operating System :: OS Independent
Requires-Python: >=3.7
Provides-Extra: dev
Requires-Dist: pytest; extra == "dev"
Requires-Dist: twine; extra == "dev"
Requires-Dist: build; extra == "dev"
Requires-Dist: black; extra == "dev"
